odoo10_addon_mrp_bom_comparison-10.0.1.0.0.99.dev8-py3.8-nspkg.pth
odoo/addons/mrp_bom_comparison/README.rst
odoo/addons/mrp_bom_comparison/__init__.py
odoo/addons/mrp_bom_comparison/__manifest__.py
odoo/addons/mrp_bom_comparison/reports.xml
odoo/addons/mrp_bom_comparison/i18n/de.po
odoo/addons/mrp_bom_comparison/i18n/mrp_bom_comparison.pot
odoo/addons/mrp_bom_comparison/readme/CONTRIBUTORS.rst
odoo/addons/mrp_bom_comparison/readme/DESCRIPTION.rst
odoo/addons/mrp_bom_comparison/readme/DEVELOP.rst
odoo/addons/mrp_bom_comparison/readme/USAGE.rst
odoo/addons/mrp_bom_comparison/reports/mrp_bom_comparison.xml
odoo/addons/mrp_bom_comparison/static/description/icon.png
odoo/addons/mrp_bom_comparison/static/description/index.html
odoo/addons/mrp_bom_comparison/tests/__init__.py
odoo/addons/mrp_bom_comparison/tests/test_mrp_bom_comparison.py
odoo/addons/mrp_bom_comparison/wizards/__init__.py
odoo/addons/mrp_bom_comparison/wizards/mrp_bom_comparison.py
odoo/addons/mrp_bom_comparison/wizards/mrp_bom_comparison.xml
odoo10_addon_mrp_bom_comparison-10.0.1.0.0.99.dev8.dist-info/METADATA
odoo10_addon_mrp_bom_comparison-10.0.1.0.0.99.dev8.dist-info/WHEEL
odoo10_addon_mrp_bom_comparison-10.0.1.0.0.99.dev8.dist-info/namespace_packages.txt
odoo10_addon_mrp_bom_comparison-10.0.1.0.0.99.dev8.dist-info/top_level.txt
odoo10_addon_mrp_bom_comparison-10.0.1.0.0.99.dev8.dist-info/RECORD
